{
  "required": true,
  "package": "dev.stardust.mixin",
  "compatibilityLevel": "JAVA_21",
  "client": [
    "ScreenMixin",
    "ChatHudMixin",
    "InGameHudMixin",
    "BossBarHudMixin",
    "BookScreenMixin",
    "DrawContextMixin",
    "SoundSystemMixin",
    "TitleScreenMixin",
    "MusicTrackerMixin",
    "GameMenuScreenMixin",
    "EntityRendererMixin",
    "BookEditScreenMixin",
    "MinecraftClientMixin",
    "NarratorManagerMixin",
    "InventoryScreenMixin",
    "WeightedSoundSetMixin",
    "accessor.StyleAccessor",
    "SplashTextRendererMixin",
    "ClientPlayerEntityMixin",
    "ElytraSoundInstanceMixin",
    "AbstractSignEditScreenMixin",
    "accessor.AnvilScreenAccessor",
    "accessor.GameOptionsAccessor",
    "accessor.MusicTrackerAccessor",
    "BannerBlockEntityRendererMixin",
    "accessor.SourceManagerAccessor",
    "accessor.BookEditScreenAccessor",
    "accessor.BookScreenContentsAccessor",
    "ClientPlayerInteractionManagerMixin",
    "AbstractSignBlockEntityRendererMixin",
    "accessor.AbstractSignEditScreenAccessor"
  ],
  "injectors": {
    "defaultRequire": 1
  },
  "mixins": [
    "WorldMixin",
    "EntityMixin",
    "ItemStackMixin",
    "DoorBlockMixin",
    "PlayerEntityMixin",
    "GoatHornItemMixin",
    "LivingEntityMixin",
    "FireworkRocketEntityMixin",
    "accessor.ClientConnectionAccessor",
    "accessor.AnvilScreenHandlerAccessor",
    "accessor.DisconnectS2CPacketAccessor",
    "accessor.PlayerMoveC2SPacketAccessor",
    "accessor.GrindstoneScreenHandlerAccessor"
  ]
}
